{
    "entities": [
        {
            "entity": "AKSSL6RWST",
            "description": "An alternative version of the K6 total score in the past year with values ranging from 0 to 1."
        },
        {
            "entity": "KSSL6RMAX",
            "description": "The maximum value of AKSSL6RWST."
        },
        {
            "entity": "WHODASTOTSC",
            "description": "A score variable related to the level of impairment for respondents' daily activities due to emotional, mental, or other difficulties."
        },
        {
            "entity": "WHODASADSC",
            "description": "An alternative version of the total WHODASTOTSC score."
        },
        {
            "entity": "SMIPPY",
            "description": "Predicted probability that a respondent has a Serious Mental Illness (SMI) based on the 2012 mental illness prediction model."
        }
    ],
    "relationships": [
        {
            "relationship": "hasMaximumValue",
            "source_entity": "AKSSL6RWST",
            "target_entity": "KSSL6RMAX",
            "description": "Indicates that KSSL6RMAX represents the maximum value of AKSSL6RWST."
        },
        {
            "relationship": "hasImpairmentScore",
            "source_entity": "Respondent",
            "target_entity": "WHODASTOTSC",
            "description": "Relates an individual's difficulty in performing daily activities to the WHODASTOTSC score."
        },
        {
            "relationship": "hasAlternativeScore",
            "source_entity": "WHODASTOTSC",
            "target_entity": "WHODASADSC",
            "description": "Defines the alternative version of the WHODASTOTSC score."
        },
        {
            "relationship": "predictsSeriousMentalIllness",
            "source_entity": "SMIPPY",
            "target_entity": "SeriousMentalIllness",
            "description": "Indicates that SMIPPY predicts the likelihood of Serious Mental Illness (SMI)."
        }
    ]
}