{
    "entities": [
        {
            "entity": "MDEAttributes",
            "description": "Attributes related to Major Depressive Episode (MDE) questions."
        },
        {
            "entity": "Flowchart",
            "description": "A visual representation including questions from the youth depression-associated module."
        },
        {
            "entity": "YouthDepressionQuestions",
            "description": "Questions associated with youth depression in the context of the survey."
        },
        {
            "entity": "CAI",
            "description": "Computer-Assisted Interviewing system used in the survey."
        },
        {
            "entity": "EditedVariableName",
            "description": "Variable names edited to assist users in mapping information back to the CAI system."
        }
    ],
    "relationships": [
        {
            "relationship": "includesQuestions",
            "source_entity": "Flowchart",
            "target_entity": "YouthDepressionQuestions",
            "description": "Indicates that the flowchart includes questions from the youth module related to depression."
        },
        {
            "relationship": "mapsBackTo",
            "source_entity": "EditedVariableName",
            "target_entity": "CAI",
            "description": "Describes how edited variable names help users map information back to the CAI system."
        },
        {
            "relationship": "containsAttributes",
            "source_entity": "Survey",
            "target_entity": "MDEAttributes",
            "description": "States that the survey contains attributes related to Major Depressive Episode (MDE)."
        }
    ]
}