{
    "entities": [
        {
            "entity": "LastAlcoholUseMonth",
            "description": "The month in which the respondent last drank an alcoholic beverage."
        },
        {
            "entity": "LastCocaineUseAge",
            "description": "The age at which the respondent last used cocaine."
        },
        {
            "entity": "CurrentYear",
            "description": "The current survey year used throughout the questions for time reference."
        },
        {
            "entity": "LastCocaineUseYear",
            "description": "The year in which the respondent last used cocaine."
        }
    ],
    "relationships": [
        {
            "relationship": "hadLastAlcoholUseMonth",
            "source_entity": "Respondent",
            "target_entity": "LastAlcoholUseMonth",
            "description": "Indicates the last month the respondent consumed alcohol."
        },
        {
            "relationship": "hadLastCocaineUseAge",
            "source_entity": "Respondent",
            "target_entity": "LastCocaineUseAge",
            "description": "Indicates the age at which the respondent last used cocaine."
        },
        {
            "relationship": "hadLastCocaineUseYear",
            "source_entity": "Respondent",
            "target_entity": "LastCocaineUseYear",
            "description": "Indicates the last year the respondent used cocaine."
        }
    ],
    "triplets": [
        {
            "subject": "LAST ALCOHOL USE",
            "predicate": "Recode",
            "object": "Month of last alcohol use"
        },
        {
            "subject": "LAST COCAINE USE AGE",
            "predicate": "Range",
            "object": "6-74"
        },
        {
            "subject": "LAST COCAINE USE YEAR",
            "predicate": "Recode",
            "object": "Year of last cocaine use"
        }
    ]
}