{
    "entities": [
        {
            "entity": "StatisticalInference",
            "description": "The process of using data analysis to deduce properties of an underlying probability distribution."
        },
        {
            "entity": "SignificanceTesting",
            "description": "A method used to determine if the observed data deviates significantly from what is expected under a null hypothesis."
        },
        {
            "entity": "PrevalenceRates",
            "description": "The proportion of a population that has a specific characteristic in a given time period."
        },
        {
            "entity": "ConfidenceIntervals",
            "description": "A range of values that is used to estimate the true value of a population parameter."
        },
        {
            "entity": "TTests",
            "description": "A type of statistical test used to compare the means of two groups."
        },
        {
            "entity": "IndependentTests",
            "description": "Tests that assume the observations or data points are not influenced by any other observations or data points."
        },
        {
            "entity": "PValue",
            "description": "A measure that helps determine the significance of results in hypothesis testing."
        },
        {
            "entity": "SamplingError",
            "description": "The error caused by observing a sample instead of the whole population."
        }
    ],
    "relationships": [
        {
            "relationship": "involvesStatisticalInference",
            "source_entity": "SignificanceTesting",
            "target_entity": "StatisticalInference",
            "description": "Significance testing is a component of statistical inference used to determine if results are significant."
        },
        {
            "relationship": "hasPrevalenceRates",
            "source_entity": "StatisticalAnalysis",
            "target_entity": "PrevalenceRates",
            "description": "Statistical analysis often includes the calculation of prevalence rates to understand the distribution of characteristics in a population."
        },
        {
            "relationship": "containsConfidenceIntervals",
            "source_entity": "StatisticalReport",
            "target_entity": "ConfidenceIntervals",
            "description": "Statistical reports may include confidence intervals to provide estimates of population parameters."
        },
        {
            "relationship": "utilizesTTests",
            "source_entity": "SignificanceTesting",
            "target_entity": "TTests",
            "description": "Significance testing may utilize t-tests to compare group means."
        },
        {
            "relationship": "assumesIndependence",
            "source_entity": "IndependentTests",
            "target_entity": "Observations",
            "description": "Independent tests assume that data points or observations are independent of each other."
        },
        {
            "relationship": "determinesSignificance",
            "source_entity": "PValue",
            "target_entity": "Results",
            "description": "The p-value is used to determine the significance of results in hypothesis testing."
        },
        {
            "relationship": "causesError",
            "source_entity": "Sampling",
            "target_entity": "SamplingError",
            "description": "Sampling can cause sampling errors because it observes a subset of the population rather than the entire population."
        }
    ],
    "triplets": [
        {
            "subject": "StatisticalAnalysis",
            "predicate": "includes",
            "object": "PrevalenceRates"
        },
        {
            "subject": "StatisticalReport",
            "predicate": "contains",
            "object": "ConfidenceIntervals"
        },
        {
            "subject": "SignificanceTesting",
            "predicate": "utilizes",
            "object": "TTests"
        },
        {
            "subject": "IndependentTests",
            "predicate": "assumes",
            "object": "Independence"
        },
        {
            "subject": "PValue",
            "predicate": "determines",
            "object": "Significance"
        },
        {
            "subject": "Sampling",
            "predicate": "causes",
            "object": "SamplingError"
        }
    ]
}