{
    "entities": [
        {
            "entity": "RXPROVIMIS",
            "description": "Variable indicating past year misuse of Provigil products."
        },
        {
            "entity": "RXZOLPMIS",
            "description": "Variable indicating past year misuse of Zolpidem products."
        },
        {
            "entity": "RXESZOMIS",
            "description": "Variable indicating past year misuse of Eszopiclone products."
        },
        {
            "entity": "OTHRSTRMMIS",
            "description": "Variable indicating past year misuse of other stimulants."
        },
        {
            "entity": "STMNMYR",
            "description": "Variable related to past year misuse of prescription stimulants."
        },
        {
            "entity": "SEDNMYR",
            "description": "Variable related to past year misuse of prescription sedatives."
        }
    ],
    "relationships": [
        {
            "relationship": "indicatesDrugMisuse",
            "source_entity": "RXPROVIMIS",
            "target_entity": "STMNMYR",
            "description": "Indicates misuse of Provigil products within the past year."
        },
        {
            "relationship": "indicatesDrugMisuse",
            "source_entity": "OTHRSTRMMIS",
            "target_entity": "STMNMYR",
            "description": "Indicates misuse of other stimulants within the past year."
        },
        {
            "relationship": "indicatesDrugMisuse",
            "source_entity": "RXZOLPMIS",
            "target_entity": "SEDNMYR",
            "description": "Indicates misuse of Zolpidem products within the past year."
        },
        {
            "relationship": "indicatesDrugMisuse",
            "source_entity": "RXESZOMIS",
            "target_entity": "SEDNMYR",
            "description": "Indicates misuse of Eszopiclone products within the past year."
        }
    ]
}