{
    "entities": [
        {
            "entity": "EcstasyUseMonth",
            "description": "The specific month when the respondent first used Ecstasy or Molly."
        },
        {
            "entity": "EcstasyUseYear",
            "description": "The year when the respondent first used Ecstasy or Molly."
        },
        {
            "entity": "EcstasyUseRecodedMonth",
            "description": "The recoded month of first Ecstasy or Molly use."
        },
        {
            "entity": "TimeSinceLastEcstasyUse",
            "description": "Time elapsed since the respondent last used Ecstasy or Molly."
        },
        {
            "entity": "TimeSinceLastKetamineUse",
            "description": "Time elapsed since the respondent last used Ketamine."
        },
        {
            "entity": "TimeSinceLastDMTAMTFoxyUse",
            "description": "Time elapsed since the respondent last used DMT, AMT, or Foxy."
        }
    ],
    "relationships": [
        {
            "relationship": "usedEcstasyInMonth",
            "source_entity": "Respondent",
            "target_entity": "EcstasyUseMonth",
            "description": "Specifies the month when the respondent first used Ecstasy or Molly."
        },
        {
            "relationship": "usedEcstasyInYear",
            "source_entity": "Respondent",
            "target_entity": "EcstasyUseYear",
            "description": "Specifies the year when the respondent first used Ecstasy or Molly."
        },
        {
            "relationship": "hasRecodedEcstasyUseMonth",
            "source_entity": "Respondent",
            "target_entity": "EcstasyUseRecodedMonth",
            "description": "Specifies the recoded month of first Ecstasy or Molly use."
        },
        {
            "relationship": "timeSinceLastEcstasyUse",
            "source_entity": "Respondent",
            "target_entity": "TimeSinceLastEcstasyUse",
            "description": "Specifies the time elapsed since the respondent last used Ecstasy or Molly."
        },
        {
            "relationship": "timeSinceLastKetamineUse",
            "source_entity": "Respondent",
            "target_entity": "TimeSinceLastKetamineUse",
            "description": "Specifies the time elapsed since the respondent last used Ketamine."
        },
        {
            "relationship": "timeSinceLastDMTAMTFoxyUse",
            "source_entity": "Respondent",
            "target_entity": "TimeSinceLastDMTAMTFoxyUse",
            "description": "Specifies the time elapsed since the respondent last used DMT, AMT, or Foxy."
        }
    ]
}