{
    "entities": [
        {
            "entity": "Substance",
            "description": "Various substances mentioned in the NSDUH dataset, which include both street names and chemical names of drugs."
        },
        {
            "entity": "SubstanceType",
            "description": "Categorization of substances based on their chemical structure or common usage."
        },
        {
            "entity": "CommonUsage",
            "description": "Typical or street names for substances as used by the population."
        }
    ],
    "relationships": [
        {
            "relationship": "hasSubstanceType",
            "source_entity": "Substance",
            "target_entity": "SubstanceType",
            "description": "Relates a given substance to its categorization type."
        },
        {
            "relationship": "hasCommonUsage",
            "source_entity": "Substance",
            "target_entity": "CommonUsage",
            "description": "Relates a substance to its street or commonly known name."
        }
    ],
    "triplets": [
        {
            "subject": "Ayahuasca, Yage, Yahe",
            "predicate": "hasSubstanceType",
            "object": "Ayahuasca"
        },
        {
            "subject": "Alpha-methyltryptamine, AMT, IT-290, 3-IT",
            "predicate": "hasSubstanceType",
            "object": "Alpha-methyltryptamine"
        },
        {
            "subject": "Paramethoxyamphetamine, PMA",
            "predicate": "hasSubstanceType",
            "object": "Paramethoxyamphetamine"
        },
        {
            "subject": "MDE, MDEA, 3,4-Methylenedioxy-N-Ethylamphetamine",
            "predicate": "hasSubstanceType",
            "object": "MDEA"
        },
        {
            "subject": "Molly; not otherwise specified",
            "predicate": "hasCommonUsage",
            "object": "MDMA"
        },
        {
            "subject": "Scop",
            "predicate": "hasSubstanceType",
            "object": "Scopolamine"
        },
        {
            "subject": "Di-isopropyl-tryptamine, DiPT",
            "predicate": "hasSubstanceType",
            "object": "Di-isopropyl-tryptamine"
        },
        {
            "subject": "2,5-Dimethoxy-4-methylphenethylamine, 2C-D",
            "predicate": "hasSubstanceType",
            "object": "2C-D"
        },
        {
            "subject": "4-AcO-DMT",
            "predicate": "hasSubstanceType",
            "object": "Psilocin"
        }
    ]
}