[
    {
        "subject": "UD5ILLANY",
        "predicate": "is a type of",
        "object": "Drug use disorder"
    },
    {
        "subject": "UD5IEMANY",
        "predicate": "is a type of",
        "object": "Drug use disorder for drugs other than marijuana"
    },
    {
        "subject": "UD5ILLALANY",
        "predicate": "is a type of",
        "object": "Drug use disorder including prescription drugs or alcohol"
    },
    {
        "subject": "UD5PSYANY",
        "predicate": "is a type of",
        "object": "Prescription psychotherapeutic use disorder"
    },
    {
        "subject": "UD5TRQSDANY",
        "predicate": "is a type of",
        "object": "Prescription tranquilizer or sedative use disorder"
    },
    {
        "subject": "UD5OPIANY",
        "predicate": "is a type of",
        "object": "Prescription opioid use disorder"
    }
]