{
    "entities": [
        {
            "entity": "MeasurementUnit",
            "description": "A unit used to measure the quantity of substances in the survey."
        },
        {
            "entity": "UnweightedFrequency",
            "description": "The count of cases in the survey reporting a specific measurement unit, without adjustments for survey design."
        },
        {
            "entity": "SubstanceMeasurement",
            "description": "Specific measurement examples including Gram, Kilogram, Ounce, Pound, Milliliter, Liter, Fluid Ounce, Gallon, Dosage Unit/Items, and Number of Plants."
        },
        {
            "entity": "MissingData",
            "description": "Indicates the cases where data is unknown or missing."
        }
    ],
    "relationships": [
        {
            "relationship": "hasUnit",
            "source_entity": "SubstanceMeasurement",
            "target_entity": "MeasurementUnit",
            "description": "The relationship indicating a specific substance measurement involves a specific unit."
        },
        {
            "relationship": "hasFrequency",
            "source_entity": "MeasurementUnit",
            "target_entity": "UnweightedFrequency",
            "description": "The relationship linking each measurement unit to its reported frequency in the survey data."
        },
        {
            "relationship": "hasMissingData",
            "source_entity": "Survey",
            "target_entity": "MissingData",
            "description": "Indicates the link between the survey data and instances where data is missing or unknown."
        }
    ]
}